legal/licence.jgoodies.binding.txt
legal/licence.jgoodies.common.txt
legal/licence.jsoup.txt
legal/licence.poi.txt
legal/licence.rtfparserkit.txt
legal/licence.sqlite-jdbc.txt
legal/licence.txt
mpxj/__init__.py
mpxj/lib/SparseBitSet-1.3.jar
mpxj/lib/apiguardian-api-1.1.2.jar
mpxj/lib/commons-codec-1.20.0.jar
mpxj/lib/commons-collections4-4.5.0.jar
mpxj/lib/commons-io-2.21.0.jar
mpxj/lib/commons-lang3-3.18.0.jar
mpxj/lib/commons-logging-1.2.jar
mpxj/lib/commons-math3-3.6.1.jar
mpxj/lib/istack-commons-runtime-4.0.1.jar
mpxj/lib/jackcess-4.0.10.jar
mpxj/lib/jackson-annotations-2.20.jar
mpxj/lib/jackson-core-2.20.1.jar
mpxj/lib/jackson-databind-2.20.1.jar
mpxj/lib/jakarta.activation-2.0.1.jar
mpxj/lib/jakarta.xml.bind-api-3.0.1.jar
mpxj/lib/jaxb-core-3.0.2.jar
mpxj/lib/jaxb-runtime-3.0.2.jar
mpxj/lib/jgoodies-binding-2.13.0.jar
mpxj/lib/jgoodies-common-1.8.1.jar
mpxj/lib/jsoup-1.21.2.jar
mpxj/lib/junit-jupiter-api-5.14.1.jar
mpxj/lib/junit-jupiter-engine-5.14.1.jar
mpxj/lib/junit-platform-commons-1.14.1.jar
mpxj/lib/junit-platform-engine-1.14.1.jar
mpxj/lib/junit-platform-launcher-1.14.1.jar
mpxj/lib/log4j-api-2.24.3.jar
mpxj/lib/mpxj.jar
mpxj/lib/opentest4j-1.3.0.jar
mpxj/lib/poi-5.5.1.jar
mpxj/lib/rtfparserkit-1.16.0.jar
mpxj/lib/sqlite-jdbc-3.51.1.0.jar
mpxj/lib/txw2-3.0.2.jar
mpxj-15.2.0.dist-info/licenses/LICENSE
mpxj-15.2.0.dist-info/METADATA
mpxj-15.2.0.dist-info/WHEEL
mpxj-15.2.0.dist-info/top_level.txt
mpxj-15.2.0.dist-info/RECORD
