Metadata-Version: 2.4
Name: mpxj
Version: 15.2.0
Summary: Python wrapper for the MPXJ Java library for manipulating project files
Home-page: https://github.com/joniles/mpxj
Author: Jon Iles
Author-email: jon@timephased.com
License: LGPL-2.0-or-later
Project-URL: Bug Tracker, https://github.com/joniles/mpxj/issues
Classifier: Programming Language :: Python :: 3
Classifier: Operating System :: OS Independent
Requires-Python: >=3.6
License-File: LICENSE
Dynamic: author
Dynamic: author-email
Dynamic: classifier
Dynamic: description
Dynamic: description-content-type
Dynamic: home-page
Dynamic: license
Dynamic: license-file
Dynamic: project-url
Dynamic: requires-python
Dynamic: summary
